[
    {
        "key": "dbln",
        "value": "%7B%2261576330418427%22%3A%22ld3Tou58%22%2C%2261565430527526%22%3A%22gG76rv01%22%2C%2261566067777839%22%3A%22pyt1Fzgs%22%2C%2261577828890444%22%3A%22fe1IkcTr%22%7D",
        "domain": "facebook.com",
        "path": "/login/device-based/",
        "hostOnly": false,
        "creation": "2025-07-07T14:34:16.486Z",
        "lastAccessed": "2025-07-07T14:34:16.486Z"
    },
    {
        "key": "datr",
        "value": "gfwtaK-iNLzMU0i3n61-eqmq",
        "domain": "facebook.com",
        "path": "/",
        "hostOnly": false,
        "creation": "2025-07-07T14:34:16.486Z",
        "lastAccessed": "2025-07-07T14:34:16.486Z"
    },
    {
        "key": "sb",
        "value": "gfwtaDDI4ts54zuHEYbvM301",
        "domain": "facebook.com",
        "path": "/",
        "hostOnly": false,
        "creation": "2025-07-07T14:34:16.486Z",
        "lastAccessed": "2025-07-07T14:34:16.486Z"
    },
    {
        "key": "vpd",
        "value": "v1%3B746x393x2.75",
        "domain": "facebook.com",
        "path": "/",
        "hostOnly": false,
        "creation": "2025-07-07T14:34:16.486Z",
        "lastAccessed": "2025-07-07T14:34:16.486Z"
    },
    {
        "key": "ps_l",
        "value": "1",
        "domain": "facebook.com",
        "path": "/",
        "hostOnly": false,
        "creation": "2025-07-07T14:34:16.486Z",
        "lastAccessed": "2025-07-07T14:34:16.486Z"
    },
    {
        "key": "ps_n",
        "value": "1",
        "domain": "facebook.com",
        "path": "/",
        "hostOnly": false,
        "creation": "2025-07-07T14:34:16.486Z",
        "lastAccessed": "2025-07-07T14:34:16.486Z"
    },
    {
        "key": "locale",
        "value": "en_GB",
        "domain": "facebook.com",
        "path": "/",
        "hostOnly": false,
        "creation": "2025-07-07T14:34:16.486Z",
        "lastAccessed": "2025-07-07T14:34:16.486Z"
    },
    {
        "key": "m_pixel_ratio",
        "value": "2.75",
        "domain": "facebook.com",
        "path": "/",
        "hostOnly": false,
        "creation": "2025-07-07T14:34:16.486Z",
        "lastAccessed": "2025-07-07T14:34:16.486Z"
    },
    {
        "key": "wd",
        "value": "393x876",
        "domain": "facebook.com",
        "path": "/",
        "hostOnly": false,
        "creation": "2025-07-07T14:34:16.486Z",
        "lastAccessed": "2025-07-07T14:34:16.486Z"
    },
    {
        "key": "pas",
        "value": "61565430527526%3AXXNXu1Lyev%2C61566067777839%3A0nkdORo2q4%2C61577828890444%3A94nTct3fnI",
        "domain": "facebook.com",
        "path": "/",
        "hostOnly": false,
        "creation": "2025-07-07T14:34:16.486Z",
        "lastAccessed": "2025-07-07T14:34:16.486Z"
    },
    {
        "key": "c_user",
        "value": "61577828890444",
        "domain": "facebook.com",
        "path": "/",
        "hostOnly": false,
        "creation": "2025-07-07T14:34:16.486Z",
        "lastAccessed": "2025-07-07T14:34:16.486Z"
    },
    {
        "key": "xs",
        "value": "47%3A9MrIX-7vNNjDGA%3A2%3A1751897119%3A-1%3A-1",
        "domain": "facebook.com",
        "path": "/",
        "hostOnly": false,
        "creation": "2025-07-07T14:34:16.486Z",
        "lastAccessed": "2025-07-07T14:34:16.486Z"
    },
    {
        "key": "fr",
        "value": "02VZcQNv2yb0Kefa4.AWfB0jVONwT1LkWJSjPc4pMQdnJeEfssqyaUMVzB8LhKGSVPa_I.BoLfyB..AAA.0.0.Boa9pL.AWcEqI-6yb52TpqTdFh4du9Axa0",
        "domain": "facebook.com",
        "path": "/",
        "hostOnly": false,
        "creation": "2025-07-07T14:34:16.486Z",
        "lastAccessed": "2025-07-07T14:34:16.486Z"
    },
    {
        "key": "fbl_st",
        "value": "101236021%3BT%3A29198311",
        "domain": "facebook.com",
        "path": "/",
        "hostOnly": false,
        "creation": "2025-07-07T14:34:16.486Z",
        "lastAccessed": "2025-07-07T14:34:16.486Z"
    },
    {
        "key": "wl_cbv",
        "value": "v2%3Bclient_version%3A2862%3Btimestamp%3A1751898699%3BCRCM%3A284285348",
        "domain": "facebook.com",
        "path": "/",
        "hostOnly": false,
        "creation": "2025-07-07T14:34:16.486Z",
        "lastAccessed": "2025-07-07T14:34:16.486Z"
    }
]
